{
  "id": "compatibility",
  "title": "ಸಂಗಣಕದ ಸಾಮರಸ್ಯ",
  "description": "Compatibility",
  "source": "@site/i18n/kn/docusaurus-plugin-content-docs/current/compatibility.md",
  "sourceDirName": ".",
  "slug": "/compatibility",
  "permalink": "/Thunderbird-Reply-with-Attachments/kn/docs/compatibility",
  "draft": false,
  "unlisted": false,
  "tags": [],
  "version": "current",
  "lastUpdatedAt": 1757726723000,
  "frontMatter": {
    "id": "compatibility",
    "title": "ಸಂಗಣಕದ ಸಾಮರಸ್ಯ",
    "sidebar_label": "ಸಂಗಣಕದ ಸಾಮರಸ್ಯ"
  },
  "sidebar": "docs",
  "previous": {
    "title": "ಬಳಕೆ",
    "permalink": "/Thunderbird-Reply-with-Attachments/kn/docs/usage"
  },
  "next": {
    "title": "ಅನುಮತಿಗಳು",
    "permalink": "/Thunderbird-Reply-with-Attachments/kn/docs/permissions"
  }
}