{
  "id": "glossary",
  "title": "ආශ්‍රිත පදය පරාසය",
  "description": "Glossary",
  "source": "@site/i18n/si/docusaurus-plugin-content-docs/current/glossary.md",
  "sourceDirName": ".",
  "slug": "/glossary",
  "permalink": "/Thunderbird-Reply-with-Attachments/si/docs/glossary",
  "draft": false,
  "unlisted": false,
  "tags": [],
  "version": "current",
  "lastUpdatedAt": 1757205965000,
  "frontMatter": {
    "id": "glossary",
    "title": "ආශ්‍රිත පදය පරාසය",
    "sidebar_label": "ආශ්‍රිත පදය පරාසය"
  },
  "sidebar": "docs",
  "previous": {
    "title": "භාෂා",
    "permalink": "/Thunderbird-Reply-with-Attachments/si/docs/languages"
  },
  "next": {
    "title": "ආධාරය",
    "permalink": "/Thunderbird-Reply-with-Attachments/si/docs/support"
  }
}