{
  "id": "install",
  "title": "Paigaldamine",
  "description": "Installation via \"Thunderbird Add-ons and Themes\"",
  "source": "@site/i18n/et/docusaurus-plugin-content-docs/current/install.md",
  "sourceDirName": ".",
  "slug": "/install",
  "permalink": "/Thunderbird-Reply-with-Attachments/et/docs/install",
  "draft": false,
  "unlisted": false,
  "tags": [],
  "version": "current",
  "lastUpdatedAt": 1757205965000,
  "frontMatter": {
    "id": "install",
    "title": "Paigaldamine",
    "slug": "/install",
    "sidebar_label": "Paigaldamine"
  },
  "sidebar": "docs",
  "previous": {
    "title": "Kiire algus",
    "permalink": "/Thunderbird-Reply-with-Attachments/et/docs/quickstart"
  },
  "next": {
    "title": "Konfiguratsioon",
    "permalink": "/Thunderbird-Reply-with-Attachments/et/docs/configuration"
  }
}