{
  "id": "glossary",
  "title": "শব্দালংকাৰ",
  "description": "Glossary",
  "source": "@site/i18n/as/docusaurus-plugin-content-docs/current/glossary.md",
  "sourceDirName": ".",
  "slug": "/glossary",
  "permalink": "/Thunderbird-Reply-with-Attachments/as/docs/glossary",
  "draft": false,
  "unlisted": false,
  "tags": [],
  "version": "current",
  "lastUpdatedAt": 1757726723000,
  "frontMatter": {
    "id": "glossary",
    "title": "শব্দালংকাৰ",
    "sidebar_label": "শব্দালংকাৰ"
  },
  "sidebar": "docs",
  "previous": {
    "title": "ভাষাসমূহ",
    "permalink": "/Thunderbird-Reply-with-Attachments/as/docs/languages"
  },
  "next": {
    "title": "সহায়তা",
    "permalink": "/Thunderbird-Reply-with-Attachments/as/docs/support"
  }
}