{
  "id": "configuration",
  "title": "ကွန်ဖစ်ဂျူရေးရှင်း",
  "description": "Configuration",
  "source": "@site/i18n/my/docusaurus-plugin-content-docs/current/configuration.md",
  "sourceDirName": ".",
  "slug": "/configuration",
  "permalink": "/Thunderbird-Reply-with-Attachments/my/docs/configuration",
  "draft": false,
  "unlisted": false,
  "tags": [],
  "version": "current",
  "lastUpdatedAt": 1757726723000,
  "frontMatter": {
    "id": "configuration",
    "title": "ကွန်ဖစ်ဂျူရေးရှင်း"
  },
  "sidebar": "docs",
  "previous": {
    "title": "တပ်ဆင်ခြင်း",
    "permalink": "/Thunderbird-Reply-with-Attachments/my/docs/install"
  },
  "next": {
    "title": "အသုံးပြုပုံ",
    "permalink": "/Thunderbird-Reply-with-Attachments/my/docs/usage"
  }
}