{
  "id": "languages",
  "title": "Γλώσσες",
  "description": "Languages",
  "source": "@site/i18n/el/docusaurus-plugin-content-docs/current/languages.md",
  "sourceDirName": ".",
  "slug": "/languages",
  "permalink": "/Thunderbird-Reply-with-Attachments/el/docs/languages",
  "draft": false,
  "unlisted": false,
  "tags": [],
  "version": "current",
  "lastUpdatedAt": 1757726723000,
  "frontMatter": {
    "id": "languages",
    "title": "Γλώσσες",
    "sidebar_label": "Γλώσσες"
  },
  "sidebar": "docs",
  "previous": {
    "title": "Ανάπτυξη",
    "permalink": "/Thunderbird-Reply-with-Attachments/el/docs/development"
  },
  "next": {
    "title": "Γλωσσάριο",
    "permalink": "/Thunderbird-Reply-with-Attachments/el/docs/glossary"
  }
}