{
  "id": "development",
  "title": "Распрацоўка",
  "description": "---",
  "source": "@site/i18n/be/docusaurus-plugin-content-docs/current/development.md",
  "sourceDirName": ".",
  "slug": "/development",
  "permalink": "/Thunderbird-Reply-with-Attachments/be/docs/development",
  "draft": false,
  "unlisted": false,
  "tags": [],
  "version": "current",
  "lastUpdatedAt": 1757726723000,
  "frontMatter": {
    "id": "development",
    "title": "Распрацоўка",
    "sidebar_label": "Распрацоўка"
  },
  "sidebar": "docs",
  "previous": {
    "title": "Дазволы",
    "permalink": "/Thunderbird-Reply-with-Attachments/be/docs/permissions"
  },
  "next": {
    "title": "Мовы",
    "permalink": "/Thunderbird-Reply-with-Attachments/be/docs/languages"
  }
}