{
  "id": "support",
  "title": "Ondersteuning",
  "description": "FAQ",
  "source": "@site/i18n/nl/docusaurus-plugin-content-docs/current/support.md",
  "sourceDirName": ".",
  "slug": "/support",
  "permalink": "/Thunderbird-Reply-with-Attachments/nl/docs/support",
  "draft": false,
  "unlisted": false,
  "tags": [],
  "version": "current",
  "lastUpdatedAt": 1757205965000,
  "frontMatter": {
    "id": "support",
    "title": "Ondersteuning",
    "sidebar_label": "Ondersteuning"
  },
  "sidebar": "docs",
  "previous": {
    "title": "Woordenlijst",
    "permalink": "/Thunderbird-Reply-with-Attachments/nl/docs/glossary"
  },
  "next": {
    "title": "Privacy",
    "permalink": "/Thunderbird-Reply-with-Attachments/nl/docs/privacy"
  }
}