{"version":{"pluginId":"default","version":"current","label":"Next","banner":null,"badge":false,"noIndex":false,"className":"docs-version-current","isLast":true,"docsSidebars":{"docs":[{"type":"link","label":"Өзгөчөлүктөр","href":"/Thunderbird-Reply-with-Attachments/ky/docs/features","docId":"features","unlisted":false},{"type":"link","label":"Тез баштоо","href":"/Thunderbird-Reply-with-Attachments/ky/docs/quickstart","docId":"quickstart","unlisted":false},{"type":"link","label":"Орнотуу","href":"/Thunderbird-Reply-with-Attachments/ky/docs/install","docId":"install","unlisted":false},{"type":"link","label":"Конфигурация","href":"/Thunderbird-Reply-with-Attachments/ky/docs/configuration","docId":"configuration","unlisted":false},{"type":"link","label":"Колдонуу","href":"/Thunderbird-Reply-with-Attachments/ky/docs/usage","docId":"usage","unlisted":false},{"type":"link","label":"Совместимость","href":"/Thunderbird-Reply-with-Attachments/ky/docs/compatibility","docId":"compatibility","unlisted":false},{"type":"link","label":"Рұксаттар","href":"/Thunderbird-Reply-with-Attachments/ky/docs/permissions","docId":"permissions","unlisted":false},{"type":"link","label":"Өнүктүрүү","href":"/Thunderbird-Reply-with-Attachments/ky/docs/development","docId":"development","unlisted":false},{"type":"link","label":"Тилдер","href":"/Thunderbird-Reply-with-Attachments/ky/docs/languages","docId":"languages","unlisted":false},{"type":"link","label":"Термини логосун","href":"/Thunderbird-Reply-with-Attachments/ky/docs/glossary","docId":"glossary","unlisted":false},{"type":"link","label":"Ж жардам","href":"/Thunderbird-Reply-with-Attachments/ky/docs/support","docId":"support","unlisted":false},{"type":"link","label":"Жеке маалыматтарды коргоо","href":"/Thunderbird-Reply-with-Attachments/ky/docs/privacy","docId":"privacy","unlisted":false},{"type":"link","label":"Донордук","href":"/Thunderbird-Reply-with-Attachments/ky/docs/donation","docId":"donation","unlisted":false},{"type":"link","label":"Лицензия","href":"/Thunderbird-Reply-with-Attachments/ky/docs/license","docId":"license","unlisted":false},{"type":"link","label":"Чанжлог","href":"/Thunderbird-Reply-with-Attachments/ky/docs/changelog","docId":"changelog","unlisted":false}]},"docs":{"changelog":{"id":"changelog","title":"Чанжлог","description":"Чанжлог","sidebar":"docs"},"compatibility":{"id":"compatibility","title":"Совместимость","description":"Compatibility","sidebar":"docs"},"configuration":{"id":"configuration","title":"Конфигурация","description":"Конфигурация","sidebar":"docs"},"development":{"id":"development","title":"Өнүктүрүү","description":"Development Guide","sidebar":"docs"},"donation":{"id":"donation","title":"Донордук","description":"Donate","sidebar":"docs"},"features":{"id":"features","title":"Өзгөчөлүктөр","description":"Features","sidebar":"docs"},"glossary":{"id":"glossary","title":"Термини логосун","description":"Glossary","sidebar":"docs"},"install":{"id":"install","title":"Орнотуу","description":"Installation via \"Thunderbird Add-ons and Themes\"","sidebar":"docs"},"languages":{"id":"languages","title":"Тилдер","description":"Тилдер","sidebar":"docs"},"license":{"id":"license","title":"Лицензия","description":"License","sidebar":"docs"},"permissions":{"id":"permissions","title":"Рұксаттар","description":"Рұксаттар","sidebar":"docs"},"privacy":{"id":"privacy","title":"Жеке маалыматтарды коргоо","description":"Жеке маалыматтарды коргоо","sidebar":"docs"},"quickstart":{"id":"quickstart","title":"Тез баштоо","description":"Quickstart","sidebar":"docs"},"support":{"id":"support","title":"Ж жардам","description":"FAQ","sidebar":"docs"},"usage":{"id":"usage","title":"Колдонуу","description":"Usage","sidebar":"docs"}}}}